odoo/addons/kubectl/LICENSE
odoo/addons/kubectl/README.rst
odoo/addons/kubectl/__init__.py
odoo/addons/kubectl/__manifest__.py
odoo/addons/kubectl/data/data.xml
odoo/addons/kubectl/demo/demo.xml
odoo/addons/kubectl/images/screen.png
odoo/addons/kubectl/models/__init__.py
odoo/addons/kubectl/models/kubectl_cluster.py
odoo/addons/kubectl/models/kubectl_context.py
odoo/addons/kubectl/models/kubectl_namespace.py
odoo/addons/kubectl/models/res_partner.py
odoo/addons/kubectl/models/res_users.py
odoo/addons/kubectl/security/ir.model.access.csv
odoo/addons/kubectl/security/security.xml
odoo/addons/kubectl/static/description/icon.png
odoo/addons/kubectl/static/description/icon.svg
odoo/addons/kubectl/static/description/index.html
odoo/addons/kubectl/static/src/css/style.css
odoo/addons/kubectl/tests/TEST_INSTRUCTIONS.rst
odoo/addons/kubectl/views/kubectl_cluster_views.xml
odoo/addons/kubectl/views/kubectl_context_views.xml
odoo/addons/kubectl/views/kubectl_namespace_views.xml
odoo/addons/kubectl/views/res_partner_views.xml
odoo/addons/kubectl/views/res_users_views.xml
odoo_addon_kubectl-18.0.1.0.0.dist-info/METADATA
odoo_addon_kubectl-18.0.1.0.0.dist-info/WHEEL
odoo_addon_kubectl-18.0.1.0.0.dist-info/top_level.txt
odoo_addon_kubectl-18.0.1.0.0.dist-info/RECORD
